boto3_assist/__init__.py
boto3_assist/aws_config.py
boto3_assist/boto3session.py
boto3_assist/connection.py
boto3_assist/connection_tracker.py
boto3_assist/http_status_codes.py
boto3_assist/role_assumption_mixin.py
boto3_assist/session_setup_mixin.py
boto3_assist/version.py
boto3_assist/aws_lambda/event_info.py
boto3_assist/aws_lambda/mock_context.py
boto3_assist/cloudwatch/cloudwatch_connection.py
boto3_assist/cloudwatch/cloudwatch_connection_tracker.py
boto3_assist/cloudwatch/cloudwatch_log_connection.py
boto3_assist/cloudwatch/cloudwatch_logs.py
boto3_assist/cloudwatch/cloudwatch_query.py
boto3_assist/cognito/cognito_authorizer.py
boto3_assist/cognito/cognito_connection.py
boto3_assist/cognito/cognito_utility.py
boto3_assist/cognito/jwks_cache.py
boto3_assist/cognito/user.py
boto3_assist/dynamodb/dynamodb.py
boto3_assist/dynamodb/dynamodb_connection.py
boto3_assist/dynamodb/dynamodb_helpers.py
boto3_assist/dynamodb/dynamodb_importer.py
boto3_assist/dynamodb/dynamodb_index.py
boto3_assist/dynamodb/dynamodb_iservice.py
boto3_assist/dynamodb/dynamodb_key.py
boto3_assist/dynamodb/dynamodb_model_base.py
boto3_assist/dynamodb/dynamodb_model_base_interfaces.py
boto3_assist/dynamodb/dynamodb_re_indexer.py
boto3_assist/dynamodb/dynamodb_reindexer.py
boto3_assist/dynamodb/dynamodb_reserved_words.py
boto3_assist/dynamodb/dynamodb_reserved_words.txt
boto3_assist/dynamodb/readme.md
boto3_assist/dynamodb/troubleshooting.md
boto3_assist/ec2/ec2_connection.py
boto3_assist/environment_services/__init__.py
boto3_assist/environment_services/environment_loader.py
boto3_assist/environment_services/environment_variables.py
boto3_assist/erc/__init__.py
boto3_assist/erc/ecr_connection.py
boto3_assist/errors/custom_exceptions.py
boto3_assist/models/serializable_model.py
boto3_assist/s3/s3.py
boto3_assist/s3/s3_bucket.py
boto3_assist/s3/s3_connection.py
boto3_assist/s3/s3_event_data.py
boto3_assist/s3/s3_object.py
boto3_assist/securityhub/securityhub.py
boto3_assist-0.35.0.dist-info/METADATA
boto3_assist-0.35.0.dist-info/WHEEL
boto3_assist-0.35.0.dist-info/licenses/LICENSE-EXPLAINED.txt
boto3_assist-0.35.0.dist-info/licenses/LICENSE.txt
boto3_assist-0.35.0.dist-info/RECORD
