Metadata-Version: 2.4
Name: boto3_assist
Version: 0.35.0
Summary: Additional boto3 wrappers to make your life a little easier
Author-email: Eric Wilson <boto3-assist@geekcafe.com>
License-File: LICENSE-EXPLAINED.txt
License-File: LICENSE.txt
Classifier: Development Status :: 4 - Beta
Classifier: License :: OSI Approved :: MIT License
Classifier: Operating System :: OS Independent
Classifier: Programming Language :: Python
Classifier: Programming Language :: Python :: 3
Classifier: Topic :: Software Development
Requires-Python: >=3.10
Requires-Dist: aws-lambda-powertools
Requires-Dist: aws-xray-sdk
Requires-Dist: boto3
Requires-Dist: jsons
Requires-Dist: pyjwt
Requires-Dist: python-dateutil
Requires-Dist: python-dotenv
Requires-Dist: pytz
Requires-Dist: requests
Requires-Dist: types-python-dateutil
